[
    {
        "type": "Feature",
        "properties": {
            "grid_id": 1,
            "time_index": {
                "0": "34.000",
                "1": "71.000",
                "2": "23.000",
                "3": "48.000",
                "4": "25.000",
                "5": "41.000",
                "6": "59.000",
                "7": "22.000",
                "8": "84.000",
                "9": "44.000",
                "10": "36.000",
                "11": "42.000",
                "12": "19.000",
                "13": "66.000",
                "14": "30.000",
                "15": "43.000",
                "16": "64.000",
                "17": "50.000",
                "18": "47.000",
                "19": "16.000",
                "20": "61.000",
                "21": "41.000",
                "22": "34.000",
                "23": "47.000",
                "24": "44.000",
                "25": "53.000",
                "26": "115.000",
                "27": "57.000",
                "28": "37.000",
                "29": "27.000",
                "30": "25.000",
                "31": "53.000",
                "32": "22.000",
                "33": "68.000",
                "34": "20.000",
                "35": "71.000",
                "36": "15.000",
                "37": "64.000",
                "38": "30.000",
                "39": "47.000",
                "40": "64.000",
                "41": "58.000",
                "42": "34.000",
                "43": "60.000",
                "44": "43.000",
                "45": "28.000",
                "46": "73.000",
                "47": "45.000",
                "48": "50.000",
                "49": "33.000",
                "50": "22.000",
                "51": "33.000",
                "52": "28.000",
                "53": "46.000",
                "54": "64.000",
                "55": "31.000",
                "56": "68.000",
                "57": "35.000",
                "58": "20.000",
                "59": "23.000",
                "60": "78.000",
                "61": "52.000",
                "62": "8.000",
                "63": "17.000",
                "64": "36.000",
                "65": "79.000",
                "66": "52.000",
                "67": "67.000",
                "68": "89.000",
                "69": "88.000",
                "70": "116.000",
                "71": "79.000",
                "72": "56.000",
                "73": "43.000",
                "74": "19.000",
                "75": "57.000",
                "76": "100.000",
                "77": "93.000",
                "78": "24.000",
                "79": "18.000",
                "80": "42.000",
                "81": "56.000",
                "82": "47.000",
                "83": "60.000",
                "84": "58.000",
                "85": "85.000",
                "86": "68.000",
                "87": "70.000",
                "88": "20.000",
                "89": "20.000",
                "90": "48.000",
                "91": "30.000",
                "92": "85.000",
                "93": "15.000",
                "94": "25.000"
            }
        },
        "geometry": {
            "type": "MultiPolygon",
            "coordinates": [
                [
                    [
                        [
                            99.26026451900012,
                            6.565822658000144
                        ],
                        [
                            99.25757897200006,
                            6.560939846000082
                        ],
                        [
                            99.247325066,
                            6.557033596000096
                        ],
                        [
                            99.21729576900006,
                            6.536932684000135
                        ],
                        [
                            99.19483483200005,
                            6.533107815000122
                        ],
                        [
                            99.1740014980002,
                            6.539007880000071
                        ],
                        [
                            99.15845787900017,
                            6.554388739000103
                        ],
                        [
                            99.17644290500002,
                            6.550197658000158
                        ],
                        [
                            99.18604576900012,
                            6.559393622000144
                        ],
                        [
                            99.19556725400011,
                            6.571234442000105
                        ],
                        [
                            99.2137150400001,
                            6.57485586100016
                        ],
                        [
                            99.206309441,
                            6.57485586100016
                        ],
                        [
                            99.23926842500006,
                            6.576808986000117
                        ],
                        [
                            99.247813347,
                            6.57485586100016
                        ],
                        [
                            99.26026451900012,
                            6.565822658000144
                        ]
                    ],
                    [
                        [
                            99.65870201900012,
                            6.492336330000157
                        ],
                        [
                            99.64682050900015,
                            6.50967031500015
                        ],
                        [
                            99.63414807500013,
                            6.552054746000167
                        ],
                        [
                            99.60027103000007,
                            6.583441473000079
                        ],
                        [
                            99.60303795700011,
                            6.596991278000132
                        ],
                        [
                            99.61394290500019,
                            6.608832098000107
                        ],
                        [
                            99.6238712900001,
                            6.622707424000097
                        ],
                        [
                            99.62598717500006,
                            6.632798570000148
                        ],
                        [
                            99.62354576900006,
                            6.651068427000126
                        ],
                        [
                            99.6238712900001,
                            6.657416083000058
                        ],
                        [
                            99.62924238400015,
                            6.663641669000114
                        ],
                        [
                            99.63640384200008,
                            6.666896877000156
                        ],
                        [
                            99.6424259770001,
                            6.671332098000136
                        ],
                        [
                            99.64503014400006,
                            6.681057033000087
                        ],
                        [
                            99.64649498800006,
                            6.699367580000143
                        ],
                        [
                            99.65064537900017,
                            6.717759507000096
                        ],
                        [
                            99.656993035,
                            6.723822333000086
                        ],
                        [
                            99.68051191500015,
                            6.672919012000165
                        ],
                        [
                            99.6802898600001,
                            6.62403914500014
                        ],
                        [
                            99.69604397700019,
                            6.587452689000145
                        ],
                        [
                            99.70443769600016,
                            6.558294989000103
                        ],
                        [
                            99.7032983730002,
                            6.544378973000121
                        ],
                        [
                            99.69971764400012,
                            6.533270575000174
                        ],
                        [
                            99.69263756600017,
                            6.528143622000172
                        ],
                        [
                            99.68360436300006,
                            6.526841539000173
                        ],
                        [
                            99.67579186300006,
                            6.524562893000109
                        ],
                        [
                            99.67237389400006,
                            6.516546942000147
                        ],
                        [
                            99.67212975400011,
                            6.507310289000188
                        ],
                        [
                            99.67042076900012,
                            6.501450914000145
                        ],
                        [
                            99.66627037900017,
                            6.497015692000076
                        ],
                        [
                            99.65870201900012,
                            6.492336330000157
                        ]
                    ],
                    [
                        [
                            99.8228271833278,
                            7.124164943757236
                        ],
                        [
                            99.82329227132126,
                            7.120521755075032
                        ],
                        [
                            99.82422244730807,
                            7.116878567292119
                        ],
                        [
                            99.82804650314372,
                            7.10716339807243
                        ],
                        [
                            99.83166385340414,
                            7.101349799054063
                        ],
                        [
                            99.83739993715736,
                            7.094063421689569
                        ],
                        [
                            99.8425159041856,
                            7.089490057919846
                        ],
                        [
                            99.8690775903585,
                            7.072488512235125
                        ],
                        [
                            99.87775923080383,
                            7.069465440277924
                        ],
                        [
                            99.88349531455722,
                            7.068767808287788
                        ],
                        [
                            99.88628584161839,
                            7.070550644996359
                        ],
                        [
                            99.89124677901563,
                            7.074813951302829
                        ],
                        [
                            99.89543257005712,
                            7.079464830337713
                        ],
                        [
                            99.8990499212168,
                            7.084839178885062
                        ],
                        [
                            99.91114220634782,
                            7.109747219558628
                        ],
                        [
                            99.91331261578469,
                            7.116568508030198
                        ],
                        [
                            99.9150179381273,
                            7.124242459022284
                        ],
                        [
                            99.9165682308392,
                            7.128815822792021
                        ],
                        [
                            99.91889367080628,
                            7.132924099467672
                        ],
                        [
                            99.92447472492861,
                            7.137342434505769
                        ],
                        [
                            99.92804039924513,
                            7.137652492868312
                        ],
                        [
                            99.93129601429965,
                            7.136670640038076
                        ],
                        [
                            99.93362145426673,
                            7.134551907444617
                        ],
                        [
                            99.93780724530816,
                            7.12966848441306
                        ],
                        [
                            99.96188846188309,
                            7.094683539313934
                        ],
                        [
                            99.97026004396596,
                            7.085149237247592
                        ],
                        [
                            99.98855350084344,
                            7.06923289628115
                        ],
                        [
                            100.00560672427096,
                            7.059233507120723
                        ],
                        [
                            100.01242801274262,
                            7.056908067153657
                        ],
                        [
                            100.01790571497682,
                            7.055977891166748
                        ],
                        [
                            100.04643110591078,
                            7.063419298162145
                        ],
                        [
                            100.05557783434963,
                            7.055512804072663
                        ],
                        [
                            100.06462121000081,
                            7.045022488497082
                        ],
                        [
                            100.06658491386273,
                            7.040061550200477
                        ],
                        [
                            100.06865197141141,
                            7.033085232097804
                        ],
                        [
                            100.07092573363568,
                            7.018564154212427
                        ],
                        [
                            100.0715458521594,
                            7.004921576369725
                        ],
                        [
                            100.07092573363568,
                            7.000735785328303
                        ],
                        [
                            100.07092573363568,
                            7.000270697334855
                        ],
                        [
                            100.07092573363568,
                            6.999728094975623
                        ],
                        [
                            100.07092573363568,
                            6.998720403723766
                        ],
                        [
                            100.07299279208374,
                            6.993733628804009
                        ],
                        [
                            100.07681684791916,
                            6.986912340332339
                        ],
                        [
                            100.0864803411948,
                            6.972882187962668
                        ],
                        [
                            100.09593712799611,
                            6.962314358021317
                        ],
                        [
                            100.10079471170658,
                            6.958206082244942
                        ],
                        [
                            100.10477379807233,
                            6.953632717575928
                        ],
                        [
                            100.12001834457098,
                            6.932135320688516
                        ],
                        [
                            100.12218875490711,
                            6.92980988252009
                        ],
                        [
                            100.12446251803075,
                            6.927872016180601
                        ],
                        [
                            100.1303536323143,
                            6.924306341864252
                        ],
                        [
                            100.13366092331293,
                            6.92306610841419
                        ],
                        [
                            100.14590823807478,
                            6.922523505155681
                        ],
                        [
                            100.14978396985427,
                            6.921748358799775
                        ],
                        [
                            100.1530395849089,
                            6.920508124450421
                        ],
                        [
                            100.16156619662266,
                            6.915547187053107
                        ],
                        [
                            100.16497684130817,
                            6.914461982334657
                        ],
                        [
                            100.18068647669966,
                            6.911361396011685
                        ],
                        [
                            100.18440717974764,
                            6.910276191293235
                        ],
                        [
                            100.19029829313175,
                            6.907382310545231
                        ],
                        [
                            100.19572431762325,
                            6.903739121863026
                        ],
                        [
                            100.21153730670133,
                            6.887926134583523
                        ],
                        [
                            100.21339765777569,
                            6.885264796932901
                        ],
                        [
                            100.21417280503104,
                            6.878598538092064
                        ],
                        [
                            100.21401777539992,
                            6.868831692029033
                        ],
                        [
                            100.2098319843586,
                            6.846636664050862
                        ],
                        [
                            100.20688642766655,
                            6.837179877249568
                        ],
                        [
                            100.20425093023621,
                            6.831056219868671
                        ],
                        [
                            100.2023905782626,
                            6.828265692807506
                        ],
                        [
                            100.20084028465149,
                            6.824054063344462
                        ],
                        [
                            100.19804975759033,
                            6.811651719851099
                        ],
                        [
                            100.19510420089816,
                            6.803512681764943
                        ],
                        [
                            100.19432905544156,
                            6.798861802730073
                        ],
                        [
                            100.1946391129047,
                            6.792479762930768
                        ],
                        [
                            100.202855666256,
                            6.765556342451319
                        ],
                        [
                            100.20456098769947,
                            6.761913153769029
                        ],
                        [
                            100.20828169074744,
                            6.756332098747421
                        ],
                        [
                            100.2098319843586,
                            6.744601548822487
                        ],
                        [
                            100.20394087097438,
                            6.709539089357506
                        ],
                        [
                            100.19920020191395,
                            6.699413639264009
                        ],
                        [
                            100.19665368700007,
                            6.702486064000155
                        ],
                        [
                            100.18755863400011,
                            6.707963766000148
                        ],
                        [
                            100.17329593900016,
                            6.703416240000195
                        ],
                        [
                            100.16683638600009,
                            6.695122172000154
                        ],
                        [
                            100.1640458580001,
                            6.683727519000158
                        ],
                        [
                            100.16275394700008,
                            6.66111908000012
                        ],
                        [
                            100.15608768800016,
                            6.620578919000195
                        ],
                        [
                            100.15717289200003,
                            6.603525696000162
                        ],
                        [
                            100.16518273900013,
                            6.580322978000154
                        ],
                        [
                            100.16719812000011,
                            6.56613779700011
                        ],
                        [
                            100.16120365400016,
                            6.557456156000143
                        ],
                        [
                            100.15241866100004,
                            6.549988912000117
                        ],
                        [
                            100.14570072500013,
                            6.539524435000175
                        ],
                        [
                            100.14482222500013,
                            6.530584412000152
                        ],
                        [
                            100.14807784100017,
                            6.513221131000137
                        ],
                        [
                            100.14849125200007,
                            6.504487814000157
                        ],
                        [
                            100.14435713700018,
                            6.479579773000182
                        ],
                        [
                            100.13557214400007,
                            6.457720643000144
                        ],
                        [
                            100.1272892590001,
                            6.442287502000141
                        ],
                        [
                            100.11996504000015,
                            6.463120835000126
                        ],
                        [
                            100.10816491,
                            6.479559637000122
                        ],
                        [
                            100.09009850400017,
                            6.484849351000179
                        ],
                        [
                            100.10230553500017,
                            6.517075914000131
                        ],
                        [
                            100.10352623800006,
                            6.53318919500019
                        ],
                        [
                            100.09351647200018,
                            6.540106512000108
                        ],
                        [
                            100.08057701900006,
                            6.536810614000075
                        ],
                        [
                            100.07292728000007,
                            6.528509833000086
                        ],
                        [
                            100.0633244150001,
                            6.506577867000161
                        ],
                        [
                            100.02995853000019,
                            6.534654039000159
                        ],
                        [
                            100.0013126960001,
                            6.567450262000165
                        ],
                        [
                            99.9978947270001,
                            6.576117255000071
                        ],
                        [
                            99.99512780000006,
                            6.587713934000178
                        ],
                        [
                            99.99122155000006,
                            6.597845770000134
                        ],
                        [
                            99.98414147200012,
                            6.602199611000131
                        ],
                        [
                            99.97144616000006,
                            6.59560781500015
                        ],
                        [
                            99.96412194100006,
                            6.59373607000019
                        ],
                        [
                            99.96094811300006,
                            6.598456122000101
                        ],
                        [
                            99.96314537900017,
                            6.605698960000126
                        ],
                        [
                            99.97217858200005,
                            6.617865302000112
                        ],
                        [
                            99.97396894600016,
                            6.622707424000097
                        ],
                        [
                            99.9715275400001,
                            6.632757880000071
                        ],
                        [
                            99.96290123800011,
                            6.649562893000081
                        ],
                        [
                            99.96094811300006,
                            6.660549221000124
                        ],
                        [
                            99.95655358200011,
                            6.664007880000128
                        ],
                        [
                            99.94703209700018,
                            6.663397528000161
                        ],
                        [
                            99.9373478520001,
                            6.66474030200007
                        ],
                        [
                            99.93311608200011,
                            6.674221096000068
                        ],
                        [
                            99.92847741000017,
                            6.692613023000106
                        ],
                        [
                            99.91749108200005,
                            6.705267645000092
                        ],
                        [
                            99.89144941500015,
                            6.725043036000102
                        ],
                        [
                            99.8675236340001,
                            6.762600002000113
                        ],
                        [
                            99.85173587300002,
                            6.776434637000108
                        ],
                        [
                            99.833750847,
                            6.770086981000176
                        ],
                        [
                            99.82488040500007,
                            6.769598700000103
                        ],
                        [
                            99.81763756600006,
                            6.782619533000087
                        ],
                        [
                            99.80958092500012,
                            6.808294989000132
                        ],
                        [
                            99.80250084700006,
                            6.817531643000109
                        ],
                        [
                            99.79721113400015,
                            6.821682033000144
                        ],
                        [
                            99.71070397200018,
                            6.854152736000131
                        ],
                        [
                            99.68580162900017,
                            6.877346096000153
                        ],
                        [
                            99.68604576900012,
                            6.917466539000173
                        ],
                        [
                            99.69044030000006,
                            6.935492255000099
                        ],
                        [
                            99.69581139400012,
                            6.937689520000092
                        ],
                        [
                            99.71021569100012,
                            6.937974351000122
                        ],
                        [
                            99.71387780000006,
                            6.942206122000144
                        ],
                        [
                            99.71290123800006,
                            6.951646226000165
                        ],
                        [
                            99.7072046230002,
                            6.961004950000103
                        ],
                        [
                            99.69629967500012,
                            6.965277411000116
                        ],
                        [
                            99.68091881600017,
                            6.973618882000082
                        ],
                        [
                            99.68213951900012,
                            6.992661851000165
                        ],
                        [
                            99.68620853000007,
                            7.013373114000089
                        ],
                        [
                            99.67920983200005,
                            7.026760158000087
                        ],
                        [
                            99.6954858730002,
                            7.059881903000118
                        ],
                        [
                            99.70573978000002,
                            7.075425523000121
                        ],
                        [
                            99.71680748800006,
                            7.081976630000099
                        ],
                        [
                            99.71998131600006,
                            7.088527736000088
                        ],
                        [
                            99.74805748800006,
                            7.126044012000108
                        ],
                        [
                            99.74560877921905,
                            7.12966384224606
                        ],
                        [
                            99.7459326518705,
                            7.12966848441306
                        ],
                        [
                            99.77037560365127,
                            7.128195706067032
                        ],
                        [
                            99.7827779480439,
                            7.129590969147927
                        ],
                        [
                            99.78835900306555,
                            7.131916409114993
                        ],
                        [
                            99.79456017481235,
                            7.135275376957097
                        ],
                        [
                            99.81383548362064,
                            7.142716783053118
                        ],
                        [
                            99.82019168499838,
                            7.14333689977812
                        ],
                        [
                            99.82406741677792,
                            7.142019151063081
                        ],
                        [
                            99.82499759276473,
                            7.13891856474001
                        ],
                        [
                            99.82484256403316,
                            7.135327052901232
                        ],
                        [
                            99.82329227132126,
                            7.128195706067032
                        ],
                        [
                            99.8228271833278,
                            7.124164943757236
                        ]
                    ],
                    [
                        [
                            99.29688561300006,
                            6.508368231000148
                        ],
                        [
                            99.28679446700019,
                            6.515448309000107
                        ],
                        [
                            99.274180535,
                            6.565578518000109
                        ],
                        [
                            99.2798771490001,
                            6.573187567000147
                        ],
                        [
                            99.28972415500019,
                            6.572943427000112
                        ],
                        [
                            99.3143009770001,
                            6.566473700000103
                        ],
                        [
                            99.31470787900011,
                            6.563544012000179
                        ],
                        [
                            99.31592858200005,
                            6.56089915600009
                        ],
                        [
                            99.32178795700011,
                            6.556545315000108
                        ],
                        [
                            99.32512454500014,
                            6.551418361000088
                        ],
                        [
                            99.32520592500012,
                            6.536810614000075
                        ],
                        [
                            99.32292728000002,
                            6.524847723000136
                        ],
                        [
                            99.31592858200005,
                            6.513820705000086
                        ],
                        [
                            99.30892988400015,
                            6.510687567000119
                        ],
                        [
                            99.29688561300006,
                            6.508368231000148
                        ]
                    ],
                    [
                        [
                            99.85206139400006,
                            6.706935940000093
                        ],
                        [
                            99.84213300900015,
                            6.711778062000164
                        ],
                        [
                            99.84522545700005,
                            6.728420315000122
                        ],
                        [
                            99.85718834700018,
                            6.736273505000113
                        ],
                        [
                            99.86255944100006,
                            6.726263739000117
                        ],
                        [
                            99.8675236340001,
                            6.710028387000179
                        ],
                        [
                            99.85206139400006,
                            6.706935940000093
                        ]
                    ],
                    [
                        [
                            99.61109459700006,
                            7.079494533000087
                        ],
                        [
                            99.5879826180001,
                            7.088202216000155
                        ],
                        [
                            99.57431074300004,
                            7.090684312000093
                        ],
                        [
                            99.5674748060002,
                            7.100612697000187
                        ],
                        [
                            99.56047610800007,
                            7.110215562000164
                        ],
                        [
                            99.55779056100008,
                            7.118882554000066
                        ],
                        [
                            99.56641686300006,
                            7.120672919000143
                        ],
                        [
                            99.57553144600016,
                            7.113104559000107
                        ],
                        [
                            99.58391360800013,
                            7.111639716000141
                        ],
                        [
                            99.5939233730002,
                            7.107570705000086
                        ],
                        [
                            99.5960392590001,
                            7.10415273600016
                        ],
                        [
                            99.59978274800008,
                            7.103705145000077
                        ],
                        [
                            99.60800214900004,
                            7.095648505000142
                        ],
                        [
                            99.61670983200005,
                            7.084173895000092
                        ],
                        [
                            99.61109459700006,
                            7.079494533000087
                        ]
                    ]
                ]
            ]
        }
    },
    {
        "type": "Feature",
        "properties": {
            "grid_id": 2,
            "time_index": {
                "0": "52.000",
                "1": "75.000",
                "2": "29.000",
                "3": "35.000",
                "4": "37.000",
                "5": "39.000",
                "6": "50.000",
                "7": "21.000",
                "8": "105.000",
                "9": "45.000",
                "10": "49.000",
                "11": "35.000",
                "12": "38.000",
                "13": "31.000",
                "14": "45.000",
                "15": "44.000",
                "16": "53.000",
                "17": "78.000",
                "18": "46.000",
                "19": "22.000",
                "20": "34.000",
                "21": "29.000",
                "22": "51.000",
                "23": "48.000",
                "24": "47.000",
                "25": "55.000",
                "26": "129.000",
                "27": "55.000",
                "28": "46.000",
                "29": "31.000",
                "30": "70.000",
                "31": "53.000",
                "32": "16.000",
                "33": "63.000",
                "34": "37.000",
                "35": "71.000",
                "36": "19.000",
                "37": "72.000",
                "38": "42.000",
                "39": "48.000",
                "40": "76.000",
                "41": "58.000",
                "42": "81.000",
                "43": "62.000",
                "44": "42.000",
                "45": "35.000",
                "46": "73.000",
                "47": "15.000",
                "48": "64.000",
                "49": "56.000",
                "50": "17.000",
                "51": "40.000",
                "52": "40.000",
                "53": "49.000",
                "54": "24.000",
                "55": "41.000",
                "56": "81.000",
                "57": "28.000",
                "58": "29.000",
                "59": "51.000",
                "60": "71.000",
                "61": "37.000",
                "62": "21.000",
                "63": "26.000",
                "64": "48.000",
                "65": "49.000",
                "66": "32.000",
                "67": "89.000",
                "68": "101.000",
                "69": "68.000",
                "70": "123.000",
                "71": "62.000",
                "72": "100.000",
                "73": "66.000",
                "74": "19.000",
                "75": "76.000",
                "76": "49.000",
                "77": "69.000",
                "78": "35.000",
                "79": "34.000",
                "80": "41.000",
                "81": "55.000",
                "82": "47.000",
                "83": "88.000",
                "84": "77.000",
                "85": "89.000",
                "86": "68.000",
                "87": "54.000",
                "88": "32.000",
                "89": "20.000",
                "90": "47.000",
                "91": "46.000",
                "92": "136.000",
                "93": "19.000",
                "94": "29.000"
            }
        },
        "geometry": {
            "type": "MultiPolygon",
            "coordinates": [
                [
                    [
                        [
                            98.35906009200019,
                            7.585842190000093
                        ],
                        [
                            98.36093183700004,
                            7.605495510000139
                        ],
                        [
                            98.36589603000019,
                            7.611110744000143
                        ],
                        [
                            98.36858157600008,
                            7.612941799000126
                        ],
                        [
                            98.37541751400008,
                            7.613063869000186
                        ],
                        [
                            98.37907962300008,
                            7.615139065000122
                        ],
                        [
                            98.38054446700019,
                            7.606105861000103
                        ],
                        [
                            98.37614993600002,
                            7.599595445000119
                        ],
                        [
                            98.372325066,
                            7.593898830000128
                        ],
                        [
                            98.36418704500008,
                            7.585842190000093
                        ],
                        [
                            98.35906009200019,
                            7.585842190000093
                        ]
                    ],
                    [
                        [
                            97.647715691,
                            8.614813544000157
                        ],
                        [
                            97.63274173300007,
                            8.639431057000166
                        ],
                        [
                            97.6287541020001,
                            8.65420156500015
                        ],
                        [
                            97.63477623800011,
                            8.656683661000088
                        ],
                        [
                            97.64210045700011,
                            8.662461656000133
                        ],
                        [
                            97.64543704500014,
                            8.659369208000058
                        ],
                        [
                            97.64462324300021,
                            8.642197984000134
                        ],
                        [
                            97.647715691,
                            8.614813544000157
                        ]
                    ],
                    [
                        [
                            98.26978600400011,
                            9.16828034100017
                        ],
                        [
                            98.26514733200011,
                            9.175604559000178
                        ],
                        [
                            98.26596113400015,
                            9.196600653000132
                        ],
                        [
                            98.27149498800006,
                            9.20193105700018
                        ],
                        [
                            98.30616295700005,
                            9.257513739000132
                        ],
                        [
                            98.31446373800011,
                            9.257595119000115
                        ],
                        [
                            98.3184513680001,
                            9.249050197000187
                        ],
                        [
                            98.30876712300014,
                            9.22964101800008
                        ],
                        [
                            98.29688561300006,
                            9.216253973000079
                        ],
                        [
                            98.2937931650001,
                            9.207953192000105
                        ],
                        [
                            98.29460696700019,
                            9.20262278900013
                        ],
                        [
                            98.29737389400006,
                            9.197251695000176
                        ],
                        [
                            98.29460696700019,
                            9.191961981000105
                        ],
                        [
                            98.2810978520001,
                            9.176052151000178
                        ],
                        [
                            98.26978600400011,
                            9.16828034100017
                        ]
                    ]
                ]
            ]
        }
    },
    {
        "type": "Feature",
        "properties": {
            "grid_id": 3,
            "time_index": {
                "0": "90.000",
                "1": "86.000",
                "2": "73.000",
                "3": "89.000",
                "4": "106.000",
                "5": "89.000",
                "6": "115.000",
                "7": "46.000",
                "8": "106.000",
                "9": "58.000",
                "10": "43.000",
                "11": "115.000",
                "12": "48.000",
                "13": "93.000",
                "14": "107.000",
                "15": "58.000",
                "16": "69.000",
                "17": "132.000",
                "18": "150.000",
                "19": "38.000",
                "20": "131.000",
                "21": "67.000",
                "22": "92.000",
                "23": "90.000",
                "24": "154.000",
                "25": "135.000",
                "26": "144.000",
                "27": "111.000",
                "28": "98.000",
                "29": "38.000",
                "30": "140.000",
                "31": "107.000",
                "32": "41.000",
                "33": "120.000",
                "34": "85.000",
                "35": "116.000",
                "36": "53.000",
                "37": "140.000",
                "38": "73.000",
                "39": "152.000",
                "40": "113.000",
                "41": "110.000",
                "42": "99.000",
                "43": "112.000",
                "44": "63.000",
                "45": "104.000",
                "46": "128.000",
                "47": "93.000",
                "48": "84.000",
                "49": "126.000",
                "50": "48.000",
                "51": "111.000",
                "52": "49.000",
                "53": "94.000",
                "54": "72.000",
                "55": "136.000",
                "56": "154.000",
                "57": "81.000",
                "58": "45.000",
                "59": "146.000",
                "60": "132.000",
                "61": "98.000",
                "62": "54.000",
                "63": "71.000",
                "64": "131.000",
                "65": "102.000",
                "66": "86.000",
                "67": "106.000",
                "68": "90.000",
                "69": "124.000",
                "70": "147.000",
                "71": "112.000",
                "72": "115.000",
                "73": "66.000",
                "74": "52.000",
                "75": "124.000",
                "76": "145.000",
                "77": "94.000",
                "78": "122.000",
                "79": "62.000",
                "80": "87.000",
                "81": "93.000",
                "82": "77.000",
                "83": "95.000",
                "84": "78.000",
                "85": "118.000",
                "86": "86.000",
                "87": "98.000",
                "88": "57.000",
                "89": "110.000",
                "90": "82.000",
                "91": "81.000",
                "92": "160.000",
                "93": "61.000",
                "94": "67.000"
            }
        },
        "geometry": {
            "type": "Polygon",
            "coordinates": [
                [
                    [
                        98.98365319100006,
                        7.835353908000144
                    ],
                    [
                        98.99097741000006,
                        7.836859442000105
                    ],
                    [
                        98.99610436300006,
                        7.835069078000117
                    ],
                    [
                        98.99724368600019,
                        7.832220770000077
                    ],
                    [
                        98.9964298840001,
                        7.82074616100013
                    ],
                    [
                        98.99366295700011,
                        7.816636460000083
                    ],
                    [
                        98.98902428500011,
                        7.814724026000121
                    ],
                    [
                        98.98617597700016,
                        7.811306057000124
                    ],
                    [
                        98.98617597700016,
                        7.805161851000136
                    ],
                    [
                        98.99048912900017,
                        7.798081773000177
                    ],
                    [
                        98.99170983200005,
                        7.787827867000146
                    ],
                    [
                        98.98633873800011,
                        7.784084377000113
                    ],
                    [
                        98.9454044930001,
                        7.834947007000139
                    ],
                    [
                        98.9414982430001,
                        7.836045640000094
                    ],
                    [
                        98.93783613400015,
                        7.838039455000128
                    ],
                    [
                        98.93734785200016,
                        7.842067776000107
                    ],
                    [
                        98.94060306100019,
                        7.848496812000107
                    ],
                    [
                        98.94483483200011,
                        7.852687893000137
                    ],
                    [
                        98.9476017590001,
                        7.853013414000159
                    ],
                    [
                        98.9515080090001,
                        7.85488515800013
                    ],
                    [
                        98.96574954500008,
                        7.852118231000162
                    ],
                    [
                        98.97803795700005,
                        7.843329169000114
                    ],
                    [
                        98.97966556100008,
                        7.836127020000077
                    ],
                    [
                        98.98365319100006,
                        7.835353908000144
                    ]
                ]
            ]
        }
    },
    {
        "type": "Feature",
        "properties": {
            "grid_id": 4,
            "time_index": {
                "0": "90.000",
                "1": "36.000",
                "2": "51.000",
                "3": "33.000",
                "4": "42.000",
                "5": "56.000",
                "6": "24.000",
                "7": "23.000",
                "8": "85.000",
                "9": "32.000",
                "10": "51.000",
                "11": "58.000",
                "12": "23.000",
                "13": "25.000",
                "14": "106.000",
                "15": "59.000",
                "16": "28.000",
                "17": "78.000",
                "18": "58.000",
                "19": "32.000",
                "20": "47.000",
                "21": "23.000",
                "22": "44.000",
                "23": "43.000",
                "24": "63.000",
                "25": "62.000",
                "26": "99.000",
                "27": "61.000",
                "28": "49.000",
                "29": "31.000",
                "30": "64.000",
                "31": "48.000",
                "32": "15.000",
                "33": "38.000",
                "34": "61.000",
                "35": "78.000",
                "36": "41.000",
                "37": "138.000",
                "38": "68.000",
                "39": "80.000",
                "40": "76.000",
                "41": "56.000",
                "42": "104.000",
                "43": "51.000",
                "44": "48.000",
                "45": "65.000",
                "46": "111.000",
                "47": "29.000",
                "48": "71.000",
                "49": "50.000",
                "50": "31.000",
                "51": "58.000",
                "52": "42.000",
                "53": "75.000",
                "54": "32.000",
                "55": "82.000",
                "56": "60.000",
                "57": "67.000",
                "58": "18.000",
                "59": "56.000",
                "60": "73.000",
                "61": "69.000",
                "62": "34.000",
                "63": "43.000",
                "64": "30.000",
                "65": "49.000",
                "66": "56.000",
                "67": "100.000",
                "68": "104.000",
                "69": "54.000",
                "70": "148.000",
                "71": "67.000",
                "72": "32.000",
                "73": "74.000",
                "74": "29.000",
                "75": "110.000",
                "76": "46.000",
                "77": "64.000",
                "78": "40.000",
                "79": "37.000",
                "80": "42.000",
                "81": "53.000",
                "82": "51.000",
                "83": "49.000",
                "84": "54.000",
                "85": "101.000",
                "86": "77.000",
                "87": "44.000",
                "88": "29.000",
                "89": "76.000",
                "90": "49.000",
                "91": "83.000",
                "92": "98.000",
                "93": "32.000",
                "94": "60.000"
            }
        },
        "geometry": {
            "type": "MultiPolygon",
            "coordinates": [
                [
                    [
                        [
                            98.46753991000017,
                            9.857530015000165
                        ],
                        [
                            98.4744572270001,
                            9.858303127000099
                        ],
                        [
                            98.466075066,
                            9.838934637000165
                        ],
                        [
                            98.46965579500008,
                            9.827460028000132
                        ],
                        [
                            98.46941165500007,
                            9.819199937000135
                        ],
                        [
                            98.46583092500006,
                            9.812689520000148
                        ],
                        [
                            98.46119225400017,
                            9.815171617000175
                        ],
                        [
                            98.45687910200016,
                            9.787095445000162
                        ],
                        [
                            98.4501838684082,
                            9.796939033468718
                        ],
                        [
                            98.4501838684082,
                            9.866208478917521
                        ],
                        [
                            98.4519962900001,
                            9.870103257000068
                        ],
                        [
                            98.4622501960001,
                            9.85940176000014
                        ],
                        [
                            98.46753991000017,
                            9.857530015000165
                        ]
                    ],
                    [
                        [
                            99.84766686300011,
                            10.11794668200011
                        ],
                        [
                            99.8489689460001,
                            10.115464585000083
                        ],
                        [
                            99.85254967500006,
                            10.110337632000068
                        ],
                        [
                            99.85092207100016,
                            10.103623765000123
                        ],
                        [
                            99.85515384200008,
                            10.101223049000083
                        ],
                        [
                            99.85694420700005,
                            10.099839585000097
                        ],
                        [
                            99.85572350400011,
                            10.094265041000185
                        ],
                        [
                            99.85832767000014,
                            10.090196031000133
                        ],
                        [
                            99.85792076900012,
                            10.086452541000185
                        ],
                        [
                            99.85466556100008,
                            10.085109768000109
                        ],
                        [
                            99.852305535,
                            10.082993882000096
                        ],
                        [
                            99.85043379000015,
                            10.076198635000168
                        ],
                        [
                            99.8479923840001,
                            10.07180410400018
                        ],
                        [
                            99.84392337300008,
                            10.0665550800001
                        ],
                        [
                            99.8411564460001,
                            10.062567450000117
                        ],
                        [
                            99.83464603000019,
                            10.059881903000147
                        ],
                        [
                            99.83277428500006,
                            10.056179104000108
                        ],
                        [
                            99.83033287900011,
                            10.065537828000132
                        ],
                        [
                            99.82626386800015,
                            10.063381252000127
                        ],
                        [
                            99.82178795700005,
                            10.064846096000096
                        ],
                        [
                            99.81934655000006,
                            10.074693101000122
                        ],
                        [
                            99.82488040500007,
                            10.081122137000122
                        ],
                        [
                            99.83033287900011,
                            10.096747137000108
                        ],
                        [
                            99.8294376960001,
                            10.10207754100017
                        ],
                        [
                            99.82520592500006,
                            10.105780341000127
                        ],
                        [
                            99.82382246200021,
                            10.110825914000145
                        ],
                        [
                            99.8260197270001,
                            10.124131578000075
                        ],
                        [
                            99.83904056100019,
                            10.120428778000132
                        ],
                        [
                            99.84294681100019,
                            10.124904690000093
                        ],
                        [
                            99.84831790500002,
                            10.120428778000132
                        ],
                        [
                            99.84766686300011,
                            10.11794668200011
                        ]
                    ]
                ]
            ]
        }
    },
    {
        "type": "Feature",
        "properties": {
            "grid_id": 5,
            "time_index": {
                "0": "59.000",
                "1": "52.000",
                "2": "31.000",
                "3": "50.000",
                "4": "64.000",
                "5": "29.000",
                "6": "37.000",
                "7": "60.000",
                "8": "91.000",
                "9": "62.000",
                "10": "42.000",
                "11": "59.000",
                "12": "20.000",
                "13": "24.000",
                "14": "77.000",
                "15": "64.000",
                "16": "40.000",
                "17": "95.000",
                "18": "71.000",
                "19": "70.000",
                "20": "40.000",
                "21": "37.000",
                "22": "34.000",
                "23": "24.000",
                "24": "57.000",
                "25": "48.000",
                "26": "119.000",
                "27": "47.000",
                "28": "41.000",
                "29": "50.000",
                "30": "95.000",
                "31": "45.000",
                "32": "25.000",
                "33": "38.000",
                "34": "86.000",
                "35": "43.000",
                "36": "22.000",
                "37": "92.000",
                "38": "51.000",
                "39": "81.000",
                "40": "71.000",
                "41": "30.000",
                "42": "71.000",
                "43": "34.000",
                "44": "69.000",
                "45": "41.000",
                "46": "60.000",
                "47": "49.000",
                "48": "57.000",
                "49": "89.000",
                "50": "69.000",
                "51": "27.000",
                "52": "42.000",
                "53": "42.000",
                "54": "38.000",
                "55": "79.000",
                "56": "46.000",
                "57": "76.000",
                "58": "20.000",
                "59": "60.000",
                "60": "85.000",
                "61": "69.000",
                "62": "54.000",
                "63": "79.000",
                "64": "76.000",
                "65": "32.000",
                "66": "64.000",
                "67": "72.000",
                "68": "44.000",
                "69": "54.000",
                "70": "115.000",
                "71": "60.000",
                "72": "38.000",
                "73": "41.000",
                "74": "39.000",
                "75": "53.000",
                "76": "78.000",
                "77": "43.000",
                "78": "63.000",
                "79": "36.000",
                "80": "37.000",
                "81": "54.000",
                "82": "56.000",
                "83": "30.000",
                "84": "64.000",
                "85": "105.000",
                "86": "49.000",
                "87": "45.000",
                "88": "29.000",
                "89": "76.000",
                "90": "54.000",
                "91": "79.000",
                "92": "66.000",
                "93": "33.000",
                "94": "67.000"
            }
        },
        "geometry": {
            "type": "Polygon",
            "coordinates": [
                [
                    [
                        100.80518639400012,
                        12.70099518400012
                    ],
                    [
                        100.80762780000012,
                        12.693793036000102
                    ],
                    [
                        100.79802493600008,
                        12.686712958000129
                    ],
                    [
                        100.79273522200018,
                        12.67544179900014
                    ],
                    [
                        100.78077233200005,
                        12.668646552000112
                    ],
                    [
                        100.77947024800002,
                        12.674831447000173
                    ],
                    [
                        100.77637780000006,
                        12.684759833000086
                    ],
                    [
                        100.76522871200015,
                        12.702826239000103
                    ],
                    [
                        100.76750735800013,
                        12.709865627000084
                    ],
                    [
                        100.77173912900011,
                        12.703762111000088
                    ],
                    [
                        100.77580813900008,
                        12.712225653000132
                    ],
                    [
                        100.78093509200019,
                        12.716131903000118
                    ],
                    [
                        100.78956139400012,
                        12.716579494000115
                    ],
                    [
                        100.80429121200021,
                        12.716579494000115
                    ],
                    [
                        100.80518639400012,
                        12.70099518400012
                    ]
                ]
            ]
        }
    },
    {
        "type": "Feature",
        "properties": {
            "grid_id": 6,
            "time_index": {
                "0": "74.000",
                "1": "135.000",
                "2": "67.000",
                "3": "75.000",
                "4": "124.000",
                "5": "61.000",
                "6": "68.000",
                "7": "50.000",
                "8": "120.000",
                "9": "97.000",
                "10": "91.000",
                "11": "99.000",
                "12": "73.000",
                "13": "92.000",
                "14": "143.000",
                "15": "108.000",
                "16": "82.000",
                "17": "125.000",
                "18": "122.000",
                "19": "86.000",
                "20": "69.000",
                "21": "101.000",
                "22": "100.000",
                "23": "97.000",
                "24": "65.000",
                "25": "143.000",
                "26": "148.000",
                "27": "91.000",
                "28": "139.000",
                "29": "45.000",
                "30": "110.000",
                "31": "100.000",
                "32": "36.000",
                "33": "85.000",
                "34": "131.000",
                "35": "136.000",
                "36": "53.000",
                "37": "150.000",
                "38": "112.000",
                "39": "167.000",
                "40": "108.000",
                "41": "104.000",
                "42": "106.000",
                "43": "161.000",
                "44": "105.000",
                "45": "89.000",
                "46": "108.000",
                "47": "153.000",
                "48": "100.000",
                "49": "113.000",
                "50": "76.000",
                "51": "68.000",
                "52": "96.000",
                "53": "103.000",
                "54": "76.000",
                "55": "146.000",
                "56": "109.000",
                "57": "112.000",
                "58": "46.000",
                "59": "121.000",
                "60": "152.000",
                "61": "84.000",
                "62": "75.000",
                "63": "143.000",
                "64": "81.000",
                "65": "66.000",
                "66": "70.000",
                "67": "102.000",
                "68": "79.000",
                "69": "107.000",
                "70": "150.000",
                "71": "126.000",
                "72": "94.000",
                "73": "98.000",
                "74": "96.000",
                "75": "116.000",
                "76": "113.000",
                "77": "81.000",
                "78": "92.000",
                "79": "81.000",
                "80": "125.000",
                "81": "103.000",
                "82": "95.000",
                "83": "164.000",
                "84": "101.000",
                "85": "145.000",
                "86": "99.000",
                "87": "91.000",
                "88": "58.000",
                "89": "100.000",
                "90": "115.000",
                "91": "109.000",
                "92": "152.000",
                "93": "77.000",
                "94": "76.000"
            }
        },
        "geometry": {
            "type": "Polygon",
            "coordinates": [
                [
                    [
                        102.5115666020001,
                        11.813706773000163
                    ],
                    [
                        102.51026451900012,
                        11.810248114000075
                    ],
                    [
                        102.50619550900015,
                        11.810695705000157
                    ],
                    [
                        102.49065188900013,
                        11.804510809000092
                    ],
                    [
                        102.49374433700021,
                        11.795355536000116
                    ],
                    [
                        102.49065188900013,
                        11.78660716400013
                    ],
                    [
                        102.48853600400011,
                        11.789292710000112
                    ],
                    [
                        102.48747806100008,
                        11.793483791000142
                    ],
                    [
                        102.48015384200008,
                        11.800034898000135
                    ],
                    [
                        102.47356204500008,
                        11.807277736000145
                    ],
                    [
                        102.46583092500006,
                        11.810248114000075
                    ],
                    [
                        102.4519962900001,
                        11.807766018000137
                    ],
                    [
                        102.4497990240001,
                        11.805283921000111
                    ],
                    [
                        102.44703209700006,
                        11.807277736000145
                    ],
                    [
                        102.44695071700008,
                        11.81244538000007
                    ],
                    [
                        102.45126386800004,
                        11.818264065000108
                    ],
                    [
                        102.45639082100016,
                        11.816636460000097
                    ],
                    [
                        102.45948326900006,
                        11.817165432000166
                    ],
                    [
                        102.47323652400004,
                        11.824977932000152
                    ],
                    [
                        102.47128339900021,
                        11.833238023000149
                    ],
                    [
                        102.4761662120001,
                        11.835313218000167
                    ],
                    [
                        102.48658287900017,
                        11.827053127000084
                    ],
                    [
                        102.50586998800011,
                        11.826605536000088
                    ],
                    [
                        102.51303144600016,
                        11.825913804000137
                    ],
                    [
                        102.5115666020001,
                        11.813706773000163
                    ]
                ]
            ]
        }
    }
]